varphi_tape/__init__.py
varphi_tape/antlr/VarphiTapeEvaluator.py
varphi_tape/antlr/VarphiTapeLexer.py
varphi_tape/antlr/VarphiTapeListener.py
varphi_tape/antlr/VarphiTapeParser.py
varphi_tape/antlr/__init__.py
varphi_tape/frontend/__init__.py
varphi_tape/frontend/frontend.py
varphi_tape/model/Tape.py
varphi_tape/model/__init__.py
varphi_tape-1.2.dist-info/LICENSE
varphi_tape-1.2.dist-info/METADATA
varphi_tape-1.2.dist-info/WHEEL
varphi_tape-1.2.dist-info/top_level.txt
varphi_tape-1.2.dist-info/RECORD
