Metadata-Version: 2.1
Name: varphi-tape
Version: 1.2
Summary: A package for parsing tape symbols for a Turing machine model using ANTLR.
Home-page: https://github.com/hassanelsheikha/varphi-tape
Author: Hassan El-Sheikha
Author-email: hassan.elsheikha@utoronto.ca
Classifier: Programming Language :: Python :: 3
Classifier: License :: OSI Approved :: GNU General Public License v3 (GPLv3)
Classifier: Operating System :: OS Independent
Requires-Python: >=3.12
License-File: LICENSE
Requires-Dist: antlr4-python3-runtime
